promemoria/__init__.py
promemoria/__main__.py
promemoria/files.py
promemoria/git.py
promemoria/help.py
promemoria/reminders.py
promemoria/utilities.py
promemoria-1.3.0.dist-info/METADATA
promemoria-1.3.0.dist-info/WHEEL
promemoria-1.3.0.dist-info/entry_points.txt
promemoria-1.3.0.dist-info/licenses/LICENSE
promemoria-1.3.0.dist-info/RECORD
