Metadata-Version: 2.1
Name: promemoria
Version: 1.3.0
Project-URL: Homepage, https://github.com/diantonioandrea/promemoria
Project-URL: Bug Tracker, https://github.com/diantonioandrea/promemoria/issues
Author-email: Andrea Di Antonio <mail@diantonioandrea.com>
License-File: LICENSE
Classifier: License :: OSI Approved :: MIT License
Classifier: Operating System :: OS Independent
Classifier: Programming Language :: Python :: 3
Requires-Python: >=3.7
Requires-Dist: colorama
Requires-Dist: requests
Requires-Dist: setuptools
